readfcs/__init__.py
readfcs/_core.py
readfcs/datasets/__init__.py
readfcs/datasets/_datasets.py
readfcs-2.1.0.dist-info/licenses/LICENSE
readfcs-2.1.0.dist-info/WHEEL
readfcs-2.1.0.dist-info/METADATA
readfcs-2.1.0.dist-info/RECORD
