Metadata-Version: 2.4
Name: readfcs
Version: 2.1.0
Summary: Parse fcs files into AnnData.
Author-email: Lamin Labs <laminlabs@gmail.com>
Classifier: License :: OSI Approved :: Apache Software License
Classifier: Programming Language :: Python :: 3.10
Classifier: Programming Language :: Python :: 3.11
Classifier: Programming Language :: Python :: 3.12
Classifier: Programming Language :: Python :: 3.13
License-File: LICENSE
Requires-Dist: flowio
Requires-Dist: anndata
Requires-Dist: pre-commit ; extra == "dev"
Requires-Dist: nox ; extra == "dev"
Requires-Dist: pytest>=6.0 ; extra == "dev"
Requires-Dist: pytest-cov ; extra == "dev"
Requires-Dist: nbproject-test ; extra == "dev"
Requires-Dist: laminci ; extra == "dev"
Project-URL: Home, https://github.com/laminlabs/readfcs
Provides-Extra: dev
